{
  "transcript": "at twilight on the twelfth day we'll have chablis\r\n",
  "words": [
    {
      "alignedWord": "at",
      "case": "success",
      "end": 0.31,
      "endOffset": 2,
      "phones": [
        {
          "duration": 0.09,
          "phone": "ae_B"
        },
        {
          "duration": 0.07,
          "phone": "t_E"
        }
      ],
      "start": 0.15,
      "startOffset": 0,
      "word": "at"
    },
    {
      "alignedWord": "twilight",
      "case": "success",
      "end": 0.73,
      "endOffset": 11,
      "phones": [
        {
          "duration": 0.07,
          "phone": "t_B"
        },
        {
          "duration": 0.08,
          "phone": "w_I"
        },
        {
          "duration": 0.06,
          "phone": "ay_I"
        },
        {
          "duration": 0.07,
          "phone": "l_I"
        },
        {
          "duration": 0.08,
          "phone": "ay_I"
        },
        {
          "duration": 0.06,
          "phone": "t_E"
        }
      ],
      "start": 0.31,
      "startOffset": 3,
      "word": "twilight"
    },
    {
      "alignedWord": "on",
      "case": "success",
      "end": 0.82,
      "endOffset": 14,
      "phones": [
        {
          "duration": 0.06,
          "phone": "aa_B"
        },
        {
          "duration": 0.03,
          "phone": "n_E"
        }
      ],
      "start": 0.73,
      "startOffset": 12,
      "word": "on"
    },
    {
      "alignedWord": "the",
      "case": "success",
      "end": 0.8799999999999999,
      "endOffset": 18,
      "phones": [
        {
          "duration": 0.04,
          "phone": "dh_B"
        },
        {
          "duration": 0.02,
          "phone": "ah_E"
        }
      ],
      "start": 0.82,
      "startOffset": 15,
      "word": "the"
    },
    {
      "alignedWord": "twelfth",
      "case": "success",
      "end": 1.2,
      "endOffset": 26,
      "phones": [
        {
          "duration": 0.09,
          "phone": "t_B"
        },
        {
          "duration": 0.02,
          "phone": "w_I"
        },
        {
          "duration": 0.09,
          "phone": "eh_I"
        },
        {
          "duration": 0.03,
          "phone": "l_I"
        },
        {
          "duration": 0.01,
          "phone": "f_I"
        },
        {
          "duration": 0.08,
          "phone": "th_E"
        }
      ],
      "start": 0.88,
      "startOffset": 19,
      "word": "twelfth"
    },
    {
      "alignedWord": "day",
      "case": "success",
      "end": 1.3699999999999999,
      "endOffset": 30,
      "phones": [
        {
          "duration": 0.08,
          "phone": "d_B"
        },
        {
          "duration": 0.09,
          "phone": "ey_E"
        }
      ],
      "start": 1.2,
      "startOffset": 27,
      "word": "day"
    },
    {
      "alignedWord": "we'll",
      "case": "success",
      "end": 1.5100000000000002,
      "endOffset": 36,
      "phones": [
        {
          "duration": 0.04,
          "phone": "w_B"
        },
        {
          "duration": 0.02,
          "phone": "ih_I"
        },
        {
          "duration": 0.08,
          "phone": "l_E"
        }
      ],
      "start": 1.37,
      "startOffset": 31,
      "word": "we'll"
    },
    {
      "alignedWord": "have",
      "case": "success",
      "end": 1.6400000000000001,
      "endOffset": 41,
      "phones": [
        {
          "duration": 0.02,
          "phone": "hh_B"
        },
        {
          "duration": 0.06,
          "phone": "ae_I"
        },
        {
          "duration": 0.05,
          "phone": "v_E"
        }
      ],
      "start": 1.51,
      "startOffset": 37,
      "word": "have"
    },
    {
      "alignedWord": "<unk>",
      "case": "success",
      "end": 1.9,
      "endOffset": 49,
      "phones": [
        {
          "duration": 0.26,
          "phone": "oov_S"
        }
      ],
      "start": 1.64,
      "startOffset": 42,
      "word": "chablis"
    }
  ]
}