{
  "transcript": "please take this dirty table cloth to the cleaners for me\r\n",
  "words": [
    {
      "alignedWord": "please",
      "case": "success",
      "end": 0.38,
      "endOffset": 6,
      "phones": [
        {
          "duration": 0.06,
          "phone": "p_B"
        },
        {
          "duration": 0.06,
          "phone": "l_I"
        },
        {
          "duration": 0.06,
          "phone": "iy_I"
        },
        {
          "duration": 0.08,
          "phone": "z_E"
        }
      ],
      "start": 0.12,
      "startOffset": 0,
      "word": "please"
    },
    {
      "alignedWord": "take",
      "case": "success",
      "end": 0.63,
      "endOffset": 11,
      "phones": [
        {
          "duration": 0.07,
          "phone": "t_B"
        },
        {
          "duration": 0.08,
          "phone": "ey_I"
        },
        {
          "duration": 0.07,
          "phone": "k_E"
        }
      ],
      "start": 0.41,
      "startOffset": 7,
      "word": "take"
    },
    {
      "alignedWord": "this",
      "case": "success",
      "end": 0.8200000000000001,
      "endOffset": 16,
      "phones": [
        {
          "duration": 0.05,
          "phone": "dh_B"
        },
        {
          "duration": 0.06,
          "phone": "ih_I"
        },
        {
          "duration": 0.08,
          "phone": "s_E"
        }
      ],
      "start": 0.63,
      "startOffset": 12,
      "word": "this"
    },
    {
      "alignedWord": "dirty",
      "case": "success",
      "end": 1.18,
      "endOffset": 22,
      "phones": [
        {
          "duration": 0.08,
          "phone": "d_B"
        },
        {
          "duration": 0.1,
          "phone": "er_I"
        },
        {
          "duration": 0.05,
          "phone": "t_I"
        },
        {
          "duration": 0.09,
          "phone": "iy_E"
        }
      ],
      "start": 0.86,
      "startOffset": 17,
      "word": "dirty"
    },
    {
      "alignedWord": "table",
      "case": "success",
      "end": 1.54,
      "endOffset": 28,
      "phones": [
        {
          "duration": 0.1,
          "phone": "t_B"
        },
        {
          "duration": 0.1,
          "phone": "ey_I"
        },
        {
          "duration": 0.02,
          "phone": "b_I"
        },
        {
          "duration": 0.04,
          "phone": "ah_I"
        },
        {
          "duration": 0.07,
          "phone": "l_E"
        }
      ],
      "start": 1.21,
      "startOffset": 23,
      "word": "table"
    },
    {
      "alignedWord": "cloth",
      "case": "success",
      "end": 1.94,
      "endOffset": 34,
      "phones": [
        {
          "duration": 0.12,
          "phone": "k_B"
        },
        {
          "duration": 0.08,
          "phone": "l_I"
        },
        {
          "duration": 0.12,
          "phone": "ao_I"
        },
        {
          "duration": 0.08,
          "phone": "th_E"
        }
      ],
      "start": 1.54,
      "startOffset": 29,
      "word": "cloth"
    },
    {
      "alignedWord": "to",
      "case": "success",
      "end": 2.06,
      "endOffset": 37,
      "phones": [
        {
          "duration": 0.07,
          "phone": "t_B"
        },
        {
          "duration": 0.04,
          "phone": "ih_E"
        }
      ],
      "start": 1.95,
      "startOffset": 35,
      "word": "to"
    },
    {
      "alignedWord": "the",
      "case": "success",
      "end": 2.17,
      "endOffset": 41,
      "phones": [
        {
          "duration": 0.05,
          "phone": "dh_B"
        },
        {
          "duration": 0.06,
          "phone": "ah_E"
        }
      ],
      "start": 2.06,
      "startOffset": 38,
      "word": "the"
    },
    {
      "alignedWord": "cleaners",
      "case": "success",
      "end": 2.63,
      "endOffset": 50,
      "phones": [
        {
          "duration": 0.11,
          "phone": "k_B"
        },
        {
          "duration": 0.05,
          "phone": "l_I"
        },
        {
          "duration": 0.08,
          "phone": "iy_I"
        },
        {
          "duration": 0.05,
          "phone": "n_I"
        },
        {
          "duration": 0.08,
          "phone": "er_I"
        },
        {
          "duration": 0.09,
          "phone": "z_E"
        }
      ],
      "start": 2.17,
      "startOffset": 42,
      "word": "cleaners"
    },
    {
      "alignedWord": "for",
      "case": "success",
      "end": 2.84,
      "endOffset": 54,
      "phones": [
        {
          "duration": 0.09,
          "phone": "f_B"
        },
        {
          "duration": 0.05,
          "phone": "ao_I"
        },
        {
          "duration": 0.07,
          "phone": "r_E"
        }
      ],
      "start": 2.63,
      "startOffset": 51,
      "word": "for"
    },
    {
      "alignedWord": "me",
      "case": "success",
      "end": 3.06,
      "endOffset": 57,
      "phones": [
        {
          "duration": 0.07,
          "phone": "m_B"
        },
        {
          "duration": 0.15,
          "phone": "iy_E"
        }
      ],
      "start": 2.84,
      "startOffset": 55,
      "word": "me"
    }
  ]
}