{
  "transcript": "he did not mind the useless kindly questions\r\n",
  "words": [
    {
      "alignedWord": "he",
      "case": "success",
      "end": 0.35,
      "endOffset": 2,
      "phones": [
        {
          "duration": 0.12,
          "phone": "hh_B"
        },
        {
          "duration": 0.09,
          "phone": "iy_E"
        }
      ],
      "start": 0.14,
      "startOffset": 0,
      "word": "he"
    },
    {
      "alignedWord": "did",
      "case": "success",
      "end": 0.5,
      "endOffset": 6,
      "phones": [
        {
          "duration": 0.03,
          "phone": "d_B"
        },
        {
          "duration": 0.06,
          "phone": "ih_I"
        },
        {
          "duration": 0.06,
          "phone": "d_E"
        }
      ],
      "start": 0.35,
      "startOffset": 3,
      "word": "did"
    },
    {
      "alignedWord": "not",
      "case": "success",
      "end": 0.74,
      "endOffset": 10,
      "phones": [
        {
          "duration": 0.05,
          "phone": "n_B"
        },
        {
          "duration": 0.13,
          "phone": "aa_I"
        },
        {
          "duration": 0.06,
          "phone": "t_E"
        }
      ],
      "start": 0.5,
      "startOffset": 7,
      "word": "not"
    },
    {
      "alignedWord": "mind",
      "case": "success",
      "end": 1.16,
      "endOffset": 15,
      "phones": [
        {
          "duration": 0.15,
          "phone": "m_B"
        },
        {
          "duration": 0.15,
          "phone": "ay_I"
        },
        {
          "duration": 0.05,
          "phone": "n_I"
        },
        {
          "duration": 0.06,
          "phone": "d_E"
        }
      ],
      "start": 0.75,
      "startOffset": 11,
      "word": "mind"
    },
    {
      "alignedWord": "the",
      "case": "success",
      "end": 1.26,
      "endOffset": 19,
      "phones": [
        {
          "duration": 0.05,
          "phone": "dh_B"
        },
        {
          "duration": 0.05,
          "phone": "iy_E"
        }
      ],
      "start": 1.16,
      "startOffset": 16,
      "word": "the"
    },
    {
      "alignedWord": "useless",
      "case": "success",
      "end": 1.76,
      "endOffset": 27,
      "phones": [
        {
          "duration": 0.11,
          "phone": "y_B"
        },
        {
          "duration": 0.09,
          "phone": "uw_I"
        },
        {
          "duration": 0.09,
          "phone": "s_I"
        },
        {
          "duration": 0.08,
          "phone": "l_I"
        },
        {
          "duration": 0.05,
          "phone": "ah_I"
        },
        {
          "duration": 0.08,
          "phone": "s_E"
        }
      ],
      "start": 1.26,
      "startOffset": 20,
      "word": "useless"
    },
    {
      "alignedWord": "kindly",
      "case": "success",
      "end": 2.2,
      "endOffset": 34,
      "phones": [
        {
          "duration": 0.09,
          "phone": "k_B"
        },
        {
          "duration": 0.1,
          "phone": "ay_I"
        },
        {
          "duration": 0.02,
          "phone": "n_I"
        },
        {
          "duration": 0.09,
          "phone": "d_I"
        },
        {
          "duration": 0.05,
          "phone": "l_I"
        },
        {
          "duration": 0.07,
          "phone": "iy_E"
        }
      ],
      "start": 1.78,
      "startOffset": 28,
      "word": "kindly"
    },
    {
      "alignedWord": "questions",
      "case": "success",
      "end": 2.72,
      "endOffset": 44,
      "phones": [
        {
          "duration": 0.08,
          "phone": "k_B"
        },
        {
          "duration": 0.05,
          "phone": "w_I"
        },
        {
          "duration": 0.1,
          "phone": "eh_I"
        },
        {
          "duration": 0.07,
          "phone": "s_I"
        },
        {
          "duration": 0.07,
          "phone": "ch_I"
        },
        {
          "duration": 0.06,
          "phone": "ah_I"
        },
        {
          "duration": 0.08,
          "phone": "n_I"
        },
        {
          "duration": 0.01,
          "phone": "z_E"
        }
      ],
      "start": 2.2,
      "startOffset": 35,
      "word": "questions"
    }
  ]
}